mouse_lib/__init__.py
mouse_lib/mouse_lib.py
CustomMouse-0.1.dist-info/METADATA
CustomMouse-0.1.dist-info/WHEEL
CustomMouse-0.1.dist-info/top_level.txt
CustomMouse-0.1.dist-info/RECORD
