Metadata-Version: 2.1
Name: CustomMouse
Version: 0.1
Summary: Кастомная либка для симуляции мышки (EAC UNDETECT)
Author: tolik_4ip
Author-email: Kakashka@gmail.com
Classifier: Programming Language :: Python :: 2
Classifier: Programming Language :: Python :: 3
Classifier: License :: OSI Approved :: MIT License
Classifier: Operating System :: OS Independent
Requires-Python: >=2.7
